{
    "id": 119550490,
    "name": "Amethyst",
    "author": "iMist",
    "creators": ["Solo created by iMist"],
    "verifier": "WPopoff",
    "verification": "https://www.youtube.com/watch?v=4lfkzz1VCbA",
    "percentToQualify": "56",
    "password": "Free to Copy",
    "records": [
        {
            "user": "Zoink",
            "link": "https://www.youtube.com/watch?v=x3Sof3yGJ5Y",
            "percent": 100,
            "hz": 240
        },
        {
            "user": "Rico",
            "link": "https://www.youtube.com/watch?v=CEHO3Rnl6Qo",
            "percent": 100,
            "hz": 240
        }
    ]
}
